pynxtools_stm/__init__.py
pynxtools_stm/analyticalplot.py
pynxtools_stm/helper.py
pynxtools_stm/reader.py
pynxtools_stm/stm_file_parser.py
pynxtools_stm/sts_file_parser.py
pynxtools_stm/nanonispy/README.md
pynxtools_stm/nanonispy/__init__.py
pynxtools_stm/nanonispy/constants.py
pynxtools_stm/nanonispy/read.py
pynxtools_stm/nanonispy/utils.py
pynxtools_stm/nomad/entrypoints.py
pynxtools_stm/nomad/nomad_example_paths.py
pynxtools_stm/nomad/examples/stm/README.md
pynxtools_stm/nomad/examples/stm/STM_nanonis_generic_5e.sxm
pynxtools_stm/nomad/examples/stm/STS.scheme.archive.yaml
pynxtools_stm/nomad/examples/stm/config_file_for_sxm.json
pynxtools_stm/nomad/examples/stm/eln_data.yaml
pynxtools_stm/nomad/examples/stm/stm_eln_example.archive.json
pynxtools_stm/nomad/examples/sts/README.md
pynxtools_stm/nomad/examples/sts/STS.scheme.archive.yaml
pynxtools_stm/nomad/examples/sts/STS_nanonis_generic_5e_1.dat
pynxtools_stm/nomad/examples/sts/config_file_for_dat.json
pynxtools_stm/nomad/examples/sts/eln_data.yaml
pynxtools_stm/nomad/examples/sts/sts_eln_example.archive.json
pynxtools_stm-1.0.11.dist-info/LICENSE
pynxtools_stm-1.0.11.dist-info/METADATA
pynxtools_stm-1.0.11.dist-info/WHEEL
pynxtools_stm-1.0.11.dist-info/entry_points.txt
pynxtools_stm-1.0.11.dist-info/top_level.txt
pynxtools_stm-1.0.11.dist-info/RECORD
