Metadata-Version: 2.1
Name: pynxtools-stm
Version: 1.0.11
Summary: A plugin for pynxtools to convert sts and stm files
Author: The NOMAD Authors
License: 
Project-URL: Homepage, https://github.com/FAIRmat-NFDI/pynxtools-stm
Project-URL: Parent Project, https://github.com/FAIRmat-NFDI
Classifier: Programming Language :: Python :: 3.8
Classifier: Programming Language :: Python :: 3.9
Classifier: Programming Language :: Python :: 3.10
Classifier: Programming Language :: Python :: 3.11
Classifier: Programming Language :: Python :: 3.12
Classifier: License :: OSI Approved :: Apache Software License
Classifier: Operating System :: OS Independent
Requires-Python: >=3.8
License-File: LICENSE
Requires-Dist: findiff
Requires-Dist: pynxtools>=0.9.0
Provides-Extra: dev
Requires-Dist: mypy; extra == "dev"
Requires-Dist: ruff>=0.6.0; extra == "dev"
Requires-Dist: pytest; extra == "dev"
Requires-Dist: pip-tools; extra == "dev"
Provides-Extra: docs
Requires-Dist: mkdocs; extra == "docs"
Requires-Dist: mkdocs-mermaid2-plugin; extra == "docs"
Requires-Dist: mkdocstrings; extra == "docs"
Requires-Dist: mkdocs-material; extra == "docs"
Requires-Dist: mkdocs-macros-plugin; extra == "docs"
